configize/__init__.py
Configize-1.0.1.dist-info/LICENSE.md
Configize-1.0.1.dist-info/LICENSE.txt
Configize-1.0.1.dist-info/METADATA
Configize-1.0.1.dist-info/WHEEL
Configize-1.0.1.dist-info/top_level.txt
Configize-1.0.1.dist-info/RECORD
