Metadata-Version: 2.1
Name: Configize
Version: 1.0.1
Summary: Load YAML configuration respecting XDG
Home-page: https://gitlab.com/aw1cks/Configize
Author: Alex Wicks
Author-email: alex@awicks.io
License: AGPLv3
Download-URL: https://gitlab.com/aw1cks/Configize
Keywords: xdg,config,configuration,library
Platform: linux
Classifier: Development Status :: 3 - Alpha
Classifier: License :: OSI Approved :: GNU Affero General Public License v3
Classifier: Operating System :: POSIX :: Linux
Classifier: Programming Language :: Python :: 3 :: Only
Classifier: Programming Language :: Python :: 3.6
Classifier: Programming Language :: Python :: 3.7
Classifier: Programming Language :: Python :: 3.8
Classifier: Programming Language :: Python :: 3.9
Classifier: Programming Language :: Python :: 3.10
Classifier: Topic :: Software Development :: Libraries :: Python Modules
Requires-Python: >=3.6
License-File: LICENSE.md
License-File: LICENSE.txt
Requires-Dist: pyxdg
Requires-Dist: pyyaml
